l0n0lkcp/__init__.py
l0n0lkcp/ikcp.py
l0n0lkcp-1.0.1.dist-info/METADATA
l0n0lkcp-1.0.1.dist-info/WHEEL
l0n0lkcp-1.0.1.dist-info/top_level.txt
l0n0lkcp-1.0.1.dist-info/RECORD
