Metadata-Version: 2.1
Name: l0n0lkcp
Version: 1.0.1
Summary: KCP协议python binding
Home-page: https://gitee.com/l00n00l/kcp
Author: l0n0l
Author-email: 1038352856@qq.com
License: UNKNOWN
Platform: UNKNOWN
Classifier: Programming Language :: Python :: 3
Classifier: License :: OSI Approved :: MIT License
Classifier: Operating System :: OS Independent
